ustackdocstheme/__init__.py
ustackdocstheme/tests/__init__.py
ustackdocstheme/tests/base.py
ustackdocstheme/tests/test_ustackdocstheme.py
ustackdocstheme/theme/ustackdocs/__init__.py
ustackdocstheme/theme/ustackdocs/css.html
ustackdocstheme/theme/ustackdocs/footer.html
ustackdocstheme/theme/ustackdocs/header.html
ustackdocstheme/theme/ustackdocs/layout.html
ustackdocstheme/theme/ustackdocs/paging.html
ustackdocstheme/theme/ustackdocs/sidebartoc_menu.html
ustackdocstheme/theme/ustackdocs/theme.conf
ustackdocstheme/theme/ustackdocs/titlerow.html
ustackdocstheme/theme/ustackdocs/static/css/ustackdocs.css
ustackdocstheme/theme/ustackdocs/static/images/logo-full.svg
ustackdocstheme/theme/ustackdocs/static/images/logo-vert.svg
ustackdocstheme2-0.0.5.dev1.dist-info/AUTHORS
ustackdocstheme2-0.0.5.dev1.dist-info/LICENSE
ustackdocstheme2-0.0.5.dev1.dist-info/METADATA
ustackdocstheme2-0.0.5.dev1.dist-info/WHEEL
ustackdocstheme2-0.0.5.dev1.dist-info/entry_points.txt
ustackdocstheme2-0.0.5.dev1.dist-info/pbr.json
ustackdocstheme2-0.0.5.dev1.dist-info/top_level.txt
ustackdocstheme2-0.0.5.dev1.dist-info/RECORD
